__init__.py
cedric-0.0.6.dist-info/METADATA
cedric-0.0.6.dist-info/WHEEL
cedric-0.0.6.dist-info/licenses/LICENSE
cli.py
cedric-0.0.6.dist-info/RECORD
