Metadata-Version: 2.1
Name: cedric
Version: 0.0.6
Summary: Cedric is a Python library designed to streamline the process of setting up a Django application.
Author-Email: Abhishek Choudhury <choudhuryabhishek76@gmail.com>
Classifier: Programming Language :: Python :: 3
Classifier: License :: OSI Approved :: MIT License
Classifier: Operating System :: OS Independent
Project-URL: Homepage, https://github.com/pypa/cedric
Project-URL: Bug tracker, https://github.com/pypa/cedric/issues
Requires-Python: >=3.8
